{
  "title": "Thư gửi cổ đông Berkshire Hathaway năm 2024",
  "original_title": "2024 Annual Letter to Shareholders",
  "author": "Warren Buffett",
  "source_type": "translated",
  "source_url": "https://www.berkshirehathaway.com/letters/2024ltr.pdf",
  "language": "vi",
  "original_language": "en",
  "extraction_date": "2026-01-04",
  "word_count": 850,
  "estimated_duration": "6:00",
  "genre": "business",
  "notes": "Vietnamese translation of key excerpts from Warren Buffett's 2024 shareholder letter"
}
